{
    "version": 1,
    "commands": [
        {
            "command": "DrawPaint",
            "visible": true,
            "paint": {
                "color": [
                    0,
                    0,
                    0,
                    0
                ],
                "blendMode": "Src"
            }
        },
        {
            "command": "DrawRect",
            "visible": true,
            "coords": [
                0,
                0,
                1280,
                180
            ],
            "paint": {
                "antiAlias": true,
                "color": [
                    255,
                    69,
                    16,
                    147
                ]
            },
            "shortDesc": " [0 0 1280 180]"
        },
        {
            "command": "Save",
            "visible": true
        },
        {
            "command": "ClipRect",
            "visible": true,
            "coords": [
                90,
                20,
                1190,
                160
            ],
            "op": "intersect",
            "antiAlias": true,
            "shortDesc": " [90 20 1190 160]"
        },
        {
            "command": "Save",
            "visible": true
        },
        {
            "command": "Concat44",
            "visible": true,
            "matrix": [
                [
                    1,
                    0,
                    0,
                    90
                ],
                [
                    0,
                    1,
                    0,
                    20
                ],
                [
                    0,
                    0,
                    1,
                    0
                ],
                [
                    0,
                    0,
                    0,
                    1
                ]
            ]
        },
        {
            "command": "DrawImageRect",
            "visible": true,
            "image": {
                "data": "data/0"
            },
            "src": [
                0,
                0,
                150,
                140
            ],
            "dst": [
                0,
                0,
                150,
                140
            ],
            "sampling": {
                "maxAniso": 0,
                "useCubic": false,
                "filter": 1,
                "mipmap": 2,
                "cubic.B": 0,
                "cubic.C": 0
            },
            "paint": {
                "antiAlias": true
            },
            "shortDesc": " [0 0 150 140]"
        },
        {
            "command": "Restore",
            "visible": true
        },
        {
            "command": "DrawTextBlob",
            "visible": true,
            "x": 270,
            "y": 55,
            "bounds": [
                -13.8831,
                -20.7139,
                284.584,
                4.54147
            ],
            "paint": {
                "antiAlias": true,
                "color": [
                    255,
                    255,
                    255,
                    255
                ]
            },
            "runs": [
                {
                    "font": {
                        "linearText": true,
                        "subpixelText": true,
                        "textSize": 18,
                        "edging": "subpixelantialias",
                        "typeface": {
                            "data": "data/1"
                        }
                    },
                    "coords": [
                        0,
                        0
                    ],
                    "glyphs": [
                        38,
                        82,
                        82,
                        78,
                        76,
                        72,
                        86,
                        3,
                        68,
                        81,
                        71,
                        3,
                        36,
                        71,
                        89,
                        72,
                        447,
                        76,
                        86,
                        76,
                        81,
                        74,
                        3,
                        38,
                        75,
                        82,
                        76,
                        70,
                        72,
                        86
                    ],
                    "positions": [
                        0,
                        13.4215,
                        24.1846,
                        34.9477,
                        45.2492,
                        49.5507,
                        59.6123,
                        68.16,
                        72.203,
                        81.8953,
                        92.5661,
                        103.606,
                        107.649,
                        119.834,
                        130.874,
                        139.717,
                        149.871,
                        162.332,
                        166.634,
                        175.181,
                        179.483,
                        190.154,
                        201.323,
                        205.366,
                        218.788,
                        229.569,
                        240.332,
                        244.634,
                        254.824,
                        264.886
                    ]
                }
            ],
            "shortDesc": " [256.117 34.2861 554.584 59.5415]"
        },
        {
            "command": "DrawTextBlob",
            "visible": true,
            "x": 270,
            "y": 78,
            "bounds": [
                -1,
                -11,
                581.831,
                4
            ],
            "paint": {
                "antiAlias": true,
                "color": [
                    255,
                    255,
                    255,
                    255
                ]
            },
            "runs": [
                {
                    "font": {
                        "linearText": true,
                        "subpixelText": true,
                        "textSize": 13,
                        "edging": "subpixelantialias",
                        "typeface": {
                            "data": "data/2"
                        }
                    },
                    "coords": [
                        0,
                        0
                    ],
                    "glyphs": [
                        52,
                        69,
                        307,
                        112,
                        91,
                        101,
                        85,
                        307,
                        112,
                        77,
                        104,
                        76,
                        307,
                        104,
                        101,
                        105,
                        102,
                        104,
                        69,
                        68,
                        307,
                        99,
                        57,
                        101,
                        104,
                        89,
                        69,
                        101,
                        102,
                        307,
                        104,
                        91,
                        307,
                        99,
                        101,
                        91,
                        111,
                        77,
                        68,
                        69,
                        307,
                        101,
                        69,
                        86,
                        69,
                        111,
                        57,
                        89,
                        104,
                        307,
                        57,
                        68,
                        111,
                        69,
                        101,
                        104,
                        77,
                        102,
                        77,
                        89,
                        75,
                        307,
                        65,
                        57,
                        102,
                        69,
                        68,
                        307,
                        91,
                        89,
                        307,
                        77,
                        89,
                        74,
                        91,
                        101,
                        88,
                        57,
                        104,
                        77,
                        91,
                        89,
                        307,
                        57,
                        65,
                        91,
                        105,
                        104,
                        307,
                        114,
                        91,
                        105,
                        101
                    ],
                    "positions": [
                        0,
                        11.6704,
                        19.2415,
                        22.8977,
                        33.2202,
                        40.9758,
                        45.8139,
                        52.8863,
                        56.5426,
                        67.1051,
                        70.1889,
                        75.0639,
                        82.7457,
                        86.4019,
                        91.1292,
                        95.9672,
                        103.52,
                        110.315,
                        114.969,
                        122.54,
                        130.609,
                        134.265,
                        142.187,
                        149.518,
                        154.8,
                        159.527,
                        167.135,
                        174.706,
                        179.544,
                        186.339,
                        189.996,
                        194.649,
                        202.405,
                        206.061,
                        213.983,
                        218.599,
                        226.096,
                        233.335,
                        236.419,
                        244.488,
                        252.059,
                        255.716,
                        260.332,
                        267.903,
                        270.987,
                        278.336,
                        285.353,
                        292.684,
                        300.292,
                        305.02,
                        308.676,
                        316.007,
                        324.076,
                        331.056,
                        338.628,
                        343.909,
                        348.636,
                        351.72,
                        358.515,
                        361.599,
                        369.207,
                        377.129,
                        380.785,
                        388.855,
                        396.186,
                        402.981,
                        410.552,
                        418.622,
                        422.278,
                        430.034,
                        437.642,
                        441.298,
                        444.382,
                        451.99,
                        456.384,
                        464.14,
                        468.978,
                        480.279,
                        487.61,
                        492.338,
                        495.421,
                        503.177,
                        510.785,
                        514.441,
                        521.772,
                        529.842,
                        537.597,
                        545.15,
                        549.877,
                        553.534,
                        560.523,
                        568.279,
                        575.831
                    ]
                }
            ],
            "shortDesc": " [269 67 851.831 82]"
        },
        {
            "command": "DrawTextBlob",
            "visible": true,
            "x": 270,
            "y": 98,
            "bounds": [
                -1,
                -11,
                566.643,
                4
            ],
            "paint": {
                "antiAlias": true,
                "color": [
                    255,
                    255,
                    255,
                    255
                ]
            },
            "runs": [
                {
                    "font": {
                        "linearText": true,
                        "subpixelText": true,
                        "textSize": 13,
                        "edging": "subpixelantialias",
                        "typeface": {
                            "data": "data/2"
                        }
                    },
                    "coords": [
                        0,
                        0
                    ],
                    "glyphs": [
                        105,
                        102,
                        69,
                        307,
                        91,
                        74,
                        307,
                        45,
                        112,
                        77,
                        104,
                        66,
                        76,
                        307,
                        57,
                        89,
                        68,
                        307,
                        104,
                        76,
                        77,
                        101,
                        68,
                        171,
                        99,
                        57,
                        101,
                        104,
                        114,
                        307,
                        112,
                        69,
                        65,
                        102,
                        77,
                        104,
                        69,
                        102,
                        307,
                        57,
                        89,
                        68,
                        307,
                        57,
                        99,
                        99,
                        86,
                        77,
                        66,
                        57,
                        104,
                        77,
                        91,
                        89,
                        102,
                        192,
                        307,
                        22,
                        74,
                        307,
                        114,
                        91,
                        105,
                        307,
                        112,
                        57,
                        89,
                        104,
                        307,
                        104,
                        91,
                        307,
                        86,
                        69,
                        57,
                        101,
                        89,
                        307,
                        88,
                        91,
                        101,
                        69,
                        307,
                        57,
                        65,
                        91,
                        105,
                        104,
                        307,
                        91,
                        105,
                        101
                    ],
                    "positions": [
                        0,
                        7.55255,
                        14.348,
                        21.919,
                        25.5753,
                        33.3309,
                        38.0213,
                        41.6775,
                        49.2116,
                        59.7741,
                        62.8579,
                        67.5113,
                        74.7684,
                        82.4502,
                        86.1065,
                        93.4374,
                        101.045,
                        109.115,
                        112.771,
                        117.646,
                        125.328,
                        128.412,
                        133.028,
                        141.098,
                        147.081,
                        155.003,
                        162.334,
                        167.615,
                        172.342,
                        179.59,
                        183.246,
                        193.569,
                        201.14,
                        209.209,
                        216.005,
                        219.089,
                        223.742,
                        231.313,
                        238.108,
                        241.765,
                        249.096,
                        256.704,
                        264.773,
                        268.429,
                        275.76,
                        283.682,
                        291.604,
                        294.688,
                        297.772,
                        305.029,
                        312.36,
                        317.087,
                        320.171,
                        327.927,
                        335.534,
                        342.33,
                        345.912,
                        349.569,
                        353.003,
                        357.694,
                        361.35,
                        368.339,
                        376.095,
                        383.647,
                        387.304,
                        397.866,
                        405.197,
                        412.805,
                        417.532,
                        421.189,
                        425.842,
                        433.598,
                        437.254,
                        440.338,
                        447.909,
                        455.24,
                        460.078,
                        467.686,
                        471.342,
                        482.643,
                        490.399,
                        495.015,
                        502.586,
                        506.242,
                        513.573,
                        521.643,
                        529.399,
                        536.951,
                        541.678,
                        545.335,
                        553.09,
                        560.643
                    ]
                }
            ],
            "shortDesc": " [269 87 836.643 102]"
        },
        {
            "command": "DrawTextBlob",
            "visible": true,
            "x": 270,
            "y": 117,
            "bounds": [
                -1,
                -11,
                576.02,
                4
            ],
            "paint": {
                "antiAlias": true,
                "color": [
                    255,
                    255,
                    255,
                    255
                ]
            },
            "runs": [
                {
                    "font": {
                        "linearText": true,
                        "subpixelText": true,
                        "textSize": 13,
                        "edging": "subpixelantialias",
                        "typeface": {
                            "data": "data/2"
                        }
                    },
                    "coords": [
                        0,
                        0
                    ],
                    "glyphs": [
                        57,
                        68,
                        111,
                        69,
                        101,
                        104,
                        77,
                        102,
                        77,
                        89,
                        75,
                        307,
                        99,
                        101,
                        57,
                        66,
                        104,
                        77,
                        66,
                        69,
                        102,
                        307,
                        57,
                        89,
                        68,
                        307,
                        114,
                        91,
                        105,
                        101,
                        307,
                        101,
                        77,
                        75,
                        76,
                        104,
                        102,
                        307,
                        104,
                        91,
                        307,
                        91,
                        99,
                        104,
                        171,
                        91,
                        105,
                        104,
                        191,
                        307,
                        66,
                        86,
                        77,
                        66,
                        85,
                        307,
                        104,
                        76,
                        69,
                        307,
                        184,
                        33,
                        99,
                        104,
                        171,
                        33,
                        105,
                        104,
                        307,
                        41,
                        101,
                        69,
                        74,
                        69,
                        101,
                        69,
                        89,
                        66,
                        69,
                        102,
                        184,
                        307,
                        65,
                        105,
                        104,
                        104,
                        91,
                        89,
                        307,
                        104,
                        91,
                        307,
                        104,
                        76,
                        69
                    ],
                    "positions": [
                        0,
                        7.33096,
                        15.4006,
                        22.3807,
                        29.9517,
                        35.2329,
                        39.9602,
                        43.044,
                        49.8394,
                        52.9232,
                        60.5312,
                        68.453,
                        72.1093,
                        80.0312,
                        84.8692,
                        92.2002,
                        99.4573,
                        104.185,
                        107.268,
                        114.525,
                        122.096,
                        128.892,
                        132.548,
                        139.879,
                        147.487,
                        155.557,
                        159.213,
                        166.202,
                        173.958,
                        181.51,
                        186.349,
                        190.005,
                        194.843,
                        197.927,
                        205.848,
                        213.53,
                        218.128,
                        224.924,
                        228.58,
                        233.233,
                        240.989,
                        244.645,
                        252.401,
                        260.323,
                        264.792,
                        270.775,
                        278.53,
                        286.083,
                        290.81,
                        294.448,
                        298.104,
                        305.361,
                        308.445,
                        311.529,
                        318.786,
                        325.858,
                        329.515,
                        334.39,
                        342.071,
                        349.642,
                        353.299,
                        358.543,
                        368.441,
                        376.362,
                        380.831,
                        386.814,
                        396.712,
                        404.264,
                        408.992,
                        412.648,
                        420.902,
                        425.519,
                        433.09,
                        437.485,
                        445.056,
                        449.672,
                        457.243,
                        464.851,
                        472.108,
                        479.679,
                        486.475,
                        491.719,
                        495.375,
                        503.445,
                        510.997,
                        515.725,
                        520.378,
                        528.134,
                        535.742,
                        539.398,
                        544.051,
                        551.807,
                        555.463,
                        560.338,
                        568.02
                    ]
                }
            ],
            "shortDesc": " [269 106 846.02 121]"
        },
        {
            "command": "DrawTextBlob",
            "visible": true,
            "x": 270,
            "y": 137,
            "bounds": [
                -1,
                -11,
                340.412,
                4
            ],
            "paint": {
                "antiAlias": true,
                "color": [
                    255,
                    255,
                    255,
                    255
                ]
            },
            "runs": [
                {
                    "font": {
                        "linearText": true,
                        "subpixelText": true,
                        "textSize": 13,
                        "edging": "subpixelantialias",
                        "typeface": {
                            "data": "data/2"
                        }
                    },
                    "coords": [
                        0,
                        0
                    ],
                    "glyphs": [
                        101,
                        77,
                        75,
                        76,
                        104,
                        307,
                        91,
                        101,
                        307,
                        105,
                        102,
                        69,
                        307,
                        104,
                        76,
                        69,
                        307,
                        89,
                        57,
                        111,
                        77,
                        75,
                        57,
                        104,
                        77,
                        91,
                        89,
                        307,
                        88,
                        69,
                        89,
                        105,
                        307,
                        57,
                        104,
                        307,
                        104,
                        76,
                        69,
                        307,
                        104,
                        91,
                        99,
                        307,
                        91,
                        74,
                        307,
                        104,
                        76,
                        69,
                        307,
                        99,
                        57,
                        75,
                        69,
                        192
                    ],
                    "positions": [
                        0,
                        4.83806,
                        7.92186,
                        15.8437,
                        23.5255,
                        28.2528,
                        31.9091,
                        39.6647,
                        44.5028,
                        48.159,
                        55.7116,
                        62.507,
                        70.078,
                        73.7343,
                        78.6093,
                        86.2911,
                        93.8621,
                        97.5184,
                        105.126,
                        112.199,
                        119.437,
                        122.521,
                        130.443,
                        137.774,
                        142.501,
                        145.585,
                        153.341,
                        160.949,
                        164.605,
                        175.906,
                        183.477,
                        191.085,
                        198.638,
                        202.294,
                        209.625,
                        214.352,
                        218.008,
                        222.883,
                        230.565,
                        238.136,
                        241.792,
                        246.446,
                        254.201,
                        262.123,
                        265.78,
                        273.535,
                        278.226,
                        281.882,
                        286.757,
                        294.439,
                        302.01,
                        305.666,
                        313.588,
                        320.919,
                        328.841,
                        336.412
                    ]
                }
            ],
            "shortDesc": " [269 126 610.412 141]"
        },
        {
            "command": "DrawRRect",
            "visible": true,
            "coords": [
                [
                    909,
                    70,
                    1078,
                    100
                ],
                [
                    4,
                    4
                ],
                [
                    4,
                    4
                ],
                [
                    4,
                    4
                ],
                [
                    4,
                    4
                ]
            ],
            "paint": {
                "antiAlias": true,
                "color": [
                    33,
                    255,
                    255,
                    255
                ]
            }
        },
        {
            "command": "Save",
            "visible": true
        },
        {
            "command": "ClipRRect",
            "visible": true,
            "coords": [
                [
                    909,
                    70,
                    1078,
                    100
                ],
                [
                    4,
                    4
                ],
                [
                    4,
                    4
                ],
                [
                    4,
                    4
                ],
                [
                    4,
                    4
                ]
            ],
            "op": "intersect",
            "antiAlias": true
        },
        {
            "command": "DrawTextBlob",
            "visible": true,
            "x": 928.688,
            "y": 89,
            "bounds": [
                -1,
                -11,
                129.919,
                4
            ],
            "paint": {
                "antiAlias": true,
                "color": [
                    255,
                    255,
                    255,
                    255
                ]
            },
            "runs": [
                {
                    "font": {
                        "linearText": true,
                        "subpixelText": true,
                        "textSize": 13,
                        "edging": "subpixelantialias",
                        "typeface": {
                            "data": "data/3"
                        }
                    },
                    "coords": [
                        0,
                        0
                    ],
                    "glyphs": [
                        33,
                        99,
                        104,
                        171,
                        91,
                        105,
                        104,
                        307,
                        41,
                        101,
                        69,
                        74,
                        69,
                        101,
                        69,
                        89,
                        66,
                        69,
                        102
                    ],
                    "positions": [
                        0,
                        10.075,
                        18.1963,
                        22.9088,
                        28.9656,
                        36.869,
                        44.7761,
                        49.7176,
                        52.9454,
                        61.3105,
                        66.1707,
                        73.8747,
                        78.5134,
                        86.2173,
                        91.0776,
                        98.7816,
                        106.707,
                        114.215,
                        121.919
                    ]
                }
            ],
            "shortDesc": " [927.688 78 1058.61 93]"
        },
        {
            "command": "Restore",
            "visible": true
        },
        {
            "command": "DrawRRect",
            "visible": true,
            "coords": [
                [
                    1088,
                    70,
                    1180,
                    100
                ],
                [
                    4,
                    4
                ],
                [
                    4,
                    4
                ],
                [
                    4,
                    4
                ],
                [
                    4,
                    4
                ]
            ],
            "paint": {
                "antiAlias": true,
                "color": [
                    255,
                    255,
                    255,
                    255
                ]
            }
        },
        {
            "command": "Save",
            "visible": true
        },
        {
            "command": "ClipRRect",
            "visible": true,
            "coords": [
                [
                    1088,
                    70,
                    1180,
                    100
                ],
                [
                    4,
                    4
                ],
                [
                    4,
                    4
                ],
                [
                    4,
                    4
                ],
                [
                    4,
                    4
                ]
            ],
            "op": "intersect",
            "antiAlias": true
        },
        {
            "command": "DrawTextBlob",
            "visible": true,
            "x": 1107.75,
            "y": 89,
            "bounds": [
                -1,
                -11,
                53.0449,
                2
            ],
            "paint": {
                "antiAlias": true
            },
            "runs": [
                {
                    "font": {
                        "linearText": true,
                        "subpixelText": true,
                        "textSize": 13,
                        "edging": "subpixelantialias",
                        "typeface": {
                            "data": "data/3"
                        }
                    },
                    "coords": [
                        0,
                        0
                    ],
                    "glyphs": [
                        41,
                        101,
                        91,
                        66,
                        69,
                        69,
                        68
                    ],
                    "positions": [
                        0,
                        8.36505,
                        13.2253,
                        21.1287,
                        28.6369,
                        36.3409,
                        44.0449
                    ]
                }
            ],
            "shortDesc": " [1106.75 78 1160.79 91]"
        },
        {
            "command": "Restore",
            "visible": true
        },
        {
            "command": "Restore",
            "visible": true
        }
    ]
}